sb2l/MATH.py
sb2l/__init__.py
sb2l/sb2l.py
sb2l-0.1.3.dist-info/LICENSE
sb2l-0.1.3.dist-info/METADATA
sb2l-0.1.3.dist-info/WHEEL
sb2l-0.1.3.dist-info/top_level.txt
sb2l-0.1.3.dist-info/RECORD
