Metadata-Version: 2.1
Name: sb2l
Version: 0.1.3
Summary: sb2l Translates the biological models written in SBML into LaTeX code to be compiled and read by human eye
Home-page: https://github.com/X-Jiang-bioe/sb2l
Author: Xieergai Jiang, Herbert Sauro
Author-email: jiangxieergai@gmail.com
License: MIT
Download-URL: https://github.com/X-Jiang-bioe/sb2l/archive/v_0.1.3.tar.gz
Keywords: SBML,LaTeX,Converter
Platform: UNKNOWN
Classifier: Development Status :: 3 - Alpha
Classifier: Intended Audience :: Science/Research
Classifier: Topic :: Software Development :: Build Tools
Classifier: License :: OSI Approved :: MIT License
Classifier: Programming Language :: Python :: 3
Classifier: Programming Language :: Python :: 3.4
Classifier: Programming Language :: Python :: 3.5
Classifier: Programming Language :: Python :: 3.6
Requires-Python: >=3
Requires-Dist: pylatex
Requires-Dist: python-libsbml
